{
  "IcoMoonType": "selection",
  "icons": [
    {
      "icon": {
        "paths": [
          "M192 448h640v128h-640v-128zM192 832h640v-128h-640v128zM192 192v128h640v-128h-640z"
        ],
        "width": 1024,
        "attrs": [],
        "isMulticolor": false,
        "isMulticolor2": false,
        "tags": ["stack", "load", "heap", "pile"],
        "grid": 16
      },
      "attrs": [],
      "properties": {
        "id": 141,
        "order": 19,
        "prevSize": 32,
        "name": "stack",
        "code": 59648
      },
      "setIdx": 0,
      "setId": 1,
      "iconIdx": 140
    }
  ],
  "height": 1024,
  "preferences": {
    "showGlyphs": true,
    "showCodes": false,
    "showQuickUse": true,
    "showQuickUse2": true,
    "showSVGs": true,
    "fontPref": {
      "prefix": "icon-",
      "metadata": {
        "fontFamily": "icomoon"
      },
      "metrics": {
        "emSize": 1024,
        "baseline": 6.25,
        "whitespace": 50
      },
      "embed": false
    },
    "imagePref": {
      "prefix": "icon-",
      "png": false,
      "useClassSelector": false,
      "color": 0,
      "bgColor": 16777215,
      "name": "Focompteur",
      "classSelector": ".icon",
      "height": 32,
      "columns": 16,
      "margin": 16
    },
    "historySize": 50,
    "gridSize": 16,
    "showLiga": false,
    "showGrid": true
  }
}
